pypgped/__init__.py
pypgped/functions.py
pypgped/pgp.py
pypgped/run.py
pypgped/window.py
pypgpeed/__init__.py
pypgpeed/functions.py
pypgpeed/pgp.py
pypgpeed/run.py
pypgpeed/window.py
pypgpeed-0.1.3.dist-info/METADATA
pypgpeed-0.1.3.dist-info/WHEEL
pypgpeed-0.1.3.dist-info/entry_points.txt
pypgpeed-0.1.3.dist-info/top_level.txt
pypgpeed-0.1.3.dist-info/RECORD
